{
  "uuid": "834186fc-441c-4509-9ee5-68a513ceefb4",
  "name": "Sales-Transactions",
  "header": true,
  "path": "data/CPG/Price-Elasticity-B2B/Raw-Data/sales_transactions.csv",
  "delimiter": ",",
  "datasetType": "CSV",
  "datasetSchema": "{colNames:[\"DISTRIBUTOR_ID\",\"CUSTOMER_ID\",\"INV_DT\",\"INV_NO\",\"INV_NO_KEY\",\"SKUID\",\"QTY\",\"GROSS\",\"UNITPRICE\",\"WEEK_NO\",\"NET_TOT_TAX\",\"ADJ_AMT\",\"CUST_DISC_AMT\",\"PRODUCT_DISC_AMT\",\"NET\"],colTypes:[\"STRING\",\"STRING\",\"STRING\",\"STRING\",\"STRING\",\"STRING\",\"INTEGER\",\"DOUBLE\",\"DOUBLE\",\"INTEGER\",\"INTEGER\",\"INTEGER\",\"INTEGER\",\"INTEGER\",\"DOUBLE\"],colFormats:[\"\",\"\",\"\",\"\",\"\",\"\",\"\",\"\",\"\",\"\",\"\",\"\",\"\",\"\",\"\"],colMLTypes:[\"TEXT\",\"TEXT\",\"TEXT\",\"TEXT\",\"TEXT\",\"TEXT\",\"NUMERIC\",\"NUMERIC\",\"NUMERIC\",\"NUMERIC\",\"NUMERIC\",\"NUMERIC\",\"NUMERIC\",\"NUMERIC\",\"NUMERIC\"]}",
  "schemaModel": {
    "schemaColList": [
      {
        "colName": "DISTRIBUTOR_ID",
        "colType": "STRING",
        "colFormat": "",
        "colMLType": "TEXT"
      },
      {
        "colName": "CUSTOMER_ID",
        "colType": "STRING",
        "colFormat": "",
        "colMLType": "TEXT"
      },
      {
        "colName": "INV_DT",
        "colType": "STRING",
        "colFormat": "",
        "colMLType": "TEXT"
      },
      {
        "colName": "INV_NO",
        "colType": "STRING",
        "colFormat": "",
        "colMLType": "TEXT"
      },
      {
        "colName": "INV_NO_KEY",
        "colType": "STRING",
        "colFormat": "",
        "colMLType": "TEXT"
      },
      {
        "colName": "SKUID",
        "colType": "STRING",
        "colFormat": "",
        "colMLType": "TEXT"
      },
      {
        "colName": "QTY",
        "colType": "INTEGER",
        "colFormat": "",
        "colMLType": "NUMERIC"
      },
      {
        "colName": "GROSS",
        "colType": "DOUBLE",
        "colFormat": "",
        "colMLType": "NUMERIC"
      },
      {
        "colName": "UNITPRICE",
        "colType": "DOUBLE",
        "colFormat": "",
        "colMLType": "NUMERIC"
      },
      {
        "colName": "WEEK_NO",
        "colType": "INTEGER",
        "colFormat": "",
        "colMLType": "NUMERIC"
      },
      {
        "colName": "NET_TOT_TAX",
        "colType": "INTEGER",
        "colFormat": "",
        "colMLType": "NUMERIC"
      },
      {
        "colName": "ADJ_AMT",
        "colType": "INTEGER",
        "colFormat": "",
        "colMLType": "NUMERIC"
      },
      {
        "colName": "CUST_DISC_AMT",
        "colType": "INTEGER",
        "colFormat": "",
        "colMLType": "NUMERIC"
      },
      {
        "colName": "PRODUCT_DISC_AMT",
        "colType": "INTEGER",
        "colFormat": "",
        "colMLType": "NUMERIC"
      },
      {
        "colName": "NET",
        "colType": "DOUBLE",
        "colFormat": "",
        "colMLType": "NUMERIC"
      }
    ]
  },
  "dropSpecialCharacterInColumnName": true,
  "multiLine": false
}