{
  "uuid": "2fc4fc4f-e995-480a-9e2b-e001b3be07dd",
  "name": "policy",
  "category": "Master Policy Data",
  "header": true,
  "path": "data/COMMON/Customer/Etl-Warranty/Raw-Data/policy.csv",
  "delimiter": ",",
  "datasetType": "CSV",
  "datasetSchema": "{colNames:[\"Policy_ID\",\"Policyholder_Name\",\"Policy_Start_Date\",\"Policy_End_Date\",\"Coverage_Details\",\"Premium_Amount\",\"Policy_Status\"],colTypes:[\"STRING\",\"STRING\",\"STRING\",\"STRING\",\"STRING\",\"DOUBLE\",\"STRING\"],colFormats:[\"\",\"\",\"\",\"\",\"\",\"\",\"\"],colMLTypes:[\"TEXT\",\"TEXT\",\"TEXT\",\"TEXT\",\"TEXT\",\"NUMERIC\",\"TEXT\"]}",
  "schemaModel": {
    "schemaColList": [
      {
        "colName": "Policy_ID",
        "colType": "STRING",
        "colFormat": "",
        "colMLType": "TEXT"
      },
      {
        "colName": "Policyholder_Name",
        "colType": "STRING",
        "colFormat": "",
        "colMLType": "TEXT"
      },
      {
        "colName": "Policy_Start_Date",
        "colType": "STRING",
        "colFormat": "",
        "colMLType": "TEXT"
      },
      {
        "colName": "Policy_End_Date",
        "colType": "STRING",
        "colFormat": "",
        "colMLType": "TEXT"
      },
      {
        "colName": "Coverage_Details",
        "colType": "STRING",
        "colFormat": "",
        "colMLType": "TEXT"
      },
      {
        "colName": "Premium_Amount",
        "colType": "DOUBLE",
        "colFormat": "",
        "colMLType": "NUMERIC"
      },
      {
        "colName": "Policy_Status",
        "colType": "STRING",
        "colFormat": "",
        "colMLType": "TEXT"
      }
    ]
  },
  "dropSpecialCharacterInColumnName": false,
  "multiLine": false
}
